bottom/__init__.py
bottom/client.py
bottom/core.py
bottom/irc/__init__.py
bottom/irc/serialize.py
bottom/unpack.py
bottom/util.py
bottom-3.0.0.dist-info/LICENSE
bottom-3.0.0.dist-info/METADATA
bottom-3.0.0.dist-info/WHEEL
bottom-3.0.0.dist-info/RECORD
