Metadata-Version: 2.3
Name: bottom
Version: 3.0.0
Summary: asyncio-based rfc2812-compliant IRC Client
License: MIT
Author: numberoverzero
Requires-Python: >=3.12
Classifier: Development Status :: 4 - Beta
